{"sports" :[{"name" :"soccer","id" :600,"uid" :"s:600","leagues" :[{"name" :"Barclays Premier League","abbreviation" :"eng.1","id" :700,"isTournament" :false,"country" :{"id" :31,"name" :"England","abbreviation" :"ENG"},"uid" :"s:600~l:700","groupId" :23,"shortName" :"Premier League","teams" :[{"id" :306,"uid" :"s:600~t:306","location" :"Hull City","name" :"Hull City","nickname" :"Tigers","abbreviation" :"HCY","color" :"FF621A","links" :{"api" :{"teams" :{"href" :"http://api.espn.com/v1/sports/soccer/eng.1/teams/306"},"news" :{"href" :"http://api.espn.com/v1/sports/soccer/eng.1/teams/306/news"},"notes" :{"href" :"http://api.espn.com/v1/sports/soccer/eng.1/teams/306/news/notes"}},"web" :{"teams" :{"href" :"http://espnfc.com/team/_/id/306/hull-city?ex_cid=espnapi_public"}}}},{"id" :318,"uid" :"s:600~t:318","location" :"Swansea City","name" :"Swansea City","nickname" :"Swans","abbreviation" :"SWC","color" :"1a1a1a","links" :{"api" :{"teams" :{"href" :"http://api.espn.com/v1/sports/soccer/eng.1/teams/318"},"news" :{"href" :"http://api.espn.com/v1/sports/soccer/eng.1/teams/318/news"},"notes" :{"href" :"http://api.espn.com/v1/sports/soccer/eng.1/teams/318/news/notes"}},"web" :{"teams" :{"href" :"http://espnfc.com/team/_/id/318/swansea-city?ex_cid=espnapi_public"}}}},{"id" :336,"uid" :"s:600~t:336","location" :"Stoke City","name" :"Stoke City","nickname" :"Potters","abbreviation" :"STC","color" :"C8142F","links" :{"api" :{"teams" :{"href" :"http://api.espn.com/v1/sports/soccer/eng.1/teams/336"},"news" :{"href" :"http://api.espn.com/v1/sports/soccer/eng.1/teams/336/news"},"notes" :{"href" :"http://api.espn.com/v1/sports/soccer/eng.1/teams/336/news/notes"}},"web" :{"teams" :{"href" :"http://espnfc.com/team/_/id/336/stoke-city?ex_cid=espnapi_public"}}}},{"id" :347,"uid" :"s:600~t:347","location" :"Cardiff City","name" :"Cardiff City","nickname" :"Bluebirds","abbreviation" :"CAR","color" :"C60000","links" :{"api" :{"teams" :{"href" :"http://api.espn.com/v1/sports/soccer/eng.1/teams/347"},"news" :{"href" :"http://api.espn.com/v1/sports/soccer/eng.1/teams/347/news"},"notes" :{"href" :"http://api.espn.com/v1/sports/soccer/eng.1/teams/347/news/notes"}},"web" :{"teams" :{"href" :"http://espnfc.com/team/_/id/347/cardiff-city?ex_cid=espnapi_public"}}}},{"id" :359,"uid" :"s:600~t:359","location" :"Arsenal","name" :"Arsenal","nickname" :"Gunners","abbreviation" :"ARS","color" :"C8142F","links" :{"api" :{"teams" :{"href" :"http://api.espn.com/v1/sports/soccer/eng.1/teams/359"},"news" :{"href" :"http://api.espn.com/v1/sports/soccer/eng.1/teams/359/news"},"notes" :{"href" :"http://api.espn.com/v1/sports/soccer/eng.1/teams/359/news/notes"}},"web" :{"teams" :{"href" :"http://espnfc.com/team/_/id/359/arsenal?ex_cid=espnapi_public"}}}},{"id" :360,"uid" :"s:600~t:360","location" :"Manchester United","name" :"Manchester United","nickname" :"Red Devils","abbreviation" :"MUN","color" :"C8142F","links" :{"api" :{"teams" :{"href" :"http://api.espn.com/v1/sports/soccer/eng.1/teams/360"},"news" :{"href" :"http://api.espn.com/v1/sports/soccer/eng.1/teams/360/news"},"notes" :{"href" :"http://api.espn.com/v1/sports/soccer/eng.1/teams/360/news/notes"}},"web" :{"teams" :{"href" :"http://espnfc.com/team/_/id/360/manchester-united?ex_cid=espnapi_public"}}}},{"id" :361,"uid" :"s:600~t:361","location" :"Newcastle United","name" :"Newcastle United","nickname" :"Magpies/Toon","abbreviation" :"NEW","color" :"1a1a1a","links" :{"api" :{"teams" :{"href" :"http://api.espn.com/v1/sports/soccer/eng.1/teams/361"},"news" :{"href" :"http://api.espn.com/v1/sports/soccer/eng.1/teams/361/news"},"notes" :{"href" :"http://api.espn.com/v1/sports/soccer/eng.1/teams/361/news/notes"}},"web" :{"teams" :{"href" :"http://espnfc.com/team/_/id/361/newcastle-united?ex_cid=espnapi_public"}}}},{"id" :362,"uid" :"s:600~t:362","location" :"Aston Villa","name" :"Aston Villa","nickname" :"Villans","abbreviation" :"AST","color" :"8E003B","links" :{"api" :{"teams" :{"href" :"http://api.espn.com/v1/sports/soccer/eng.1/teams/362"},"news" :{"href" :"http://api.espn.com/v1/sports/soccer/eng.1/teams/362/news"},"notes" :{"href" :"http://api.espn.com/v1/sports/soccer/eng.1/teams/362/news/notes"}},"web" :{"teams" :{"href" :"http://espnfc.com/team/_/id/362/aston-villa?ex_cid=espnapi_public"}}}},{"id" :363,"uid" :"s:600~t:363","location" :"Chelsea","name" :"Chelsea","nickname" :"Blues","abbreviation" :"CHL","color" :"000099","links" :{"api" :{"teams" :{"href" :"http://api.espn.com/v1/sports/soccer/eng.1/teams/363"},"news" :{"href" :"http://api.espn.com/v1/sports/soccer/eng.1/teams/363/news"},"notes" :{"href" :"http://api.espn.com/v1/sports/soccer/eng.1/teams/363/news/notes"}},"web" :{"teams" :{"href" :"http://espnfc.com/team/_/id/363/chelsea?ex_cid=espnapi_public"}}}},{"id" :364,"uid" :"s:600~t:364","location" :"Liverpool","name" :"Liverpool","nickname" :"Reds","abbreviation" :"LIV","color" :"C8142F","links" :{"api" :{"teams" :{"href" :"http://api.espn.com/v1/sports/soccer/eng.1/teams/364"},"news" :{"href" :"http://api.espn.com/v1/sports/soccer/eng.1/teams/364/news"},"notes" :{"href" :"http://api.espn.com/v1/sports/soccer/eng.1/teams/364/news/notes"}},"web" :{"teams" :{"href" :"http://espnfc.com/team/_/id/364/liverpool?ex_cid=espnapi_public"}}}},{"id" :366,"uid" :"s:600~t:366","location" :"Sunderland","name" :"Sunderland","nickname" :"Black Cats/Wearsiders","abbreviation" :"SUN","color" :"C8142F","links" :{"api" :{"teams" :{"href" :"http://api.espn.com/v1/sports/soccer/eng.1/teams/366"},"news" :{"href" :"http://api.espn.com/v1/sports/soccer/eng.1/teams/366/news"},"notes" :{"href" :"http://api.espn.com/v1/sports/soccer/eng.1/teams/366/news/notes"}},"web" :{"teams" :{"href" :"http://espnfc.com/team/_/id/366/sunderland?ex_cid=espnapi_public"}}}},{"id" :367,"uid" :"s:600~t:367","location" :"Tottenham Hotspur","name" :"Tottenham Hotspur","nickname" :"Spurs","abbreviation" :"TOT","color" :"2F2F86","links" :{"api" :{"teams" :{"href" :"http://api.espn.com/v1/sports/soccer/eng.1/teams/367"},"news" :{"href" :"http://api.espn.com/v1/sports/soccer/eng.1/teams/367/news"},"notes" :{"href" :"http://api.espn.com/v1/sports/soccer/eng.1/teams/367/news/notes"}},"web" :{"teams" :{"href" :"http://espnfc.com/team/_/id/367/tottenham-hotspur?ex_cid=espnapi_public"}}}},{"id" :368,"uid" :"s:600~t:368","location" :"Everton","name" :"Everton","nickname" :"Toffees","abbreviation" :"EVE","color" :"000099","links" :{"api" :{"teams" :{"href" :"http://api.espn.com/v1/sports/soccer/eng.1/teams/368"},"news" :{"href" :"http://api.espn.com/v1/sports/soccer/eng.1/teams/368/news"},"notes" :{"href" :"http://api.espn.com/v1/sports/soccer/eng.1/teams/368/news/notes"}},"web" :{"teams" :{"href" :"http://espnfc.com/team/_/id/368/everton?ex_cid=espnapi_public"}}}},{"id" :370,"uid" :"s:600~t:370","location" :"Fulham","name" :"Fulham","nickname" :"Cottagers","abbreviation" :"FUL","color" :"1a1a1a","links" :{"api" :{"teams" :{"href" :"http://api.espn.com/v1/sports/soccer/eng.1/teams/370"},"news" :{"href" :"http://api.espn.com/v1/sports/soccer/eng.1/teams/370/news"},"notes" :{"href" :"http://api.espn.com/v1/sports/soccer/eng.1/teams/370/news/notes"}},"web" :{"teams" :{"href" :"http://espnfc.com/team/_/id/370/fulham?ex_cid=espnapi_public"}}}},{"id" :371,"uid" :"s:600~t:371","location" :"West Ham United","name" :"West Ham United","nickname" :"Hammers/Iron","abbreviation" :"WHU","color" :"8E003B","links" :{"api" :{"teams" :{"href" :"http://api.espn.com/v1/sports/soccer/eng.1/teams/371"},"news" :{"href" :"http://api.espn.com/v1/sports/soccer/eng.1/teams/371/news"},"notes" :{"href" :"http://api.espn.com/v1/sports/soccer/eng.1/teams/371/news/notes"}},"web" :{"teams" :{"href" :"http://espnfc.com/team/_/id/371/west-ham-united?ex_cid=espnapi_public"}}}},{"id" :376,"uid" :"s:600~t:376","location" :"Southampton","name" :"Southampton","nickname" :"Saints","abbreviation" :"SOT","color" :"C8142F","links" :{"api" :{"teams" :{"href" :"http://api.espn.com/v1/sports/soccer/eng.1/teams/376"},"news" :{"href" :"http://api.espn.com/v1/sports/soccer/eng.1/teams/376/news"},"notes" :{"href" :"http://api.espn.com/v1/sports/soccer/eng.1/teams/376/news/notes"}},"web" :{"teams" :{"href" :"http://espnfc.com/team/_/id/376/southampton?ex_cid=espnapi_public"}}}},{"id" :381,"uid" :"s:600~t:381","location" :"Norwich City","name" :"Norwich City","nickname" :"Canaries","abbreviation" :"NOR","color" :"ffff00","links" :{"api" :{"teams" :{"href" :"http://api.espn.com/v1/sports/soccer/eng.1/teams/381"},"news" :{"href" :"http://api.espn.com/v1/sports/soccer/eng.1/teams/381/news"},"notes" :{"href" :"http://api.espn.com/v1/sports/soccer/eng.1/teams/381/news/notes"}},"web" :{"teams" :{"href" :"http://espnfc.com/team/_/id/381/norwich-city?ex_cid=espnapi_public"}}}},{"id" :382,"uid" :"s:600~t:382","location" :"Manchester City","name" :"Manchester City","nickname" :"City","abbreviation" :"MCY","color" :"0093EC","links" :{"api" :{"teams" :{"href" :"http://api.espn.com/v1/sports/soccer/eng.1/teams/382"},"news" :{"href" :"http://api.espn.com/v1/sports/soccer/eng.1/teams/382/news"},"notes" :{"href" :"http://api.espn.com/v1/sports/soccer/eng.1/teams/382/news/notes"}},"web" :{"teams" :{"href" :"http://espnfc.com/team/_/id/382/manchester-city?ex_cid=espnapi_public"}}}},{"id" :383,"uid" :"s:600~t:383","location" :"West Bromwich Albion","name" :"West Bromwich Albion","nickname" :"Baggies","abbreviation" :"WBA","color" :"2F2F86","links" :{"api" :{"teams" :{"href" :"http://api.espn.com/v1/sports/soccer/eng.1/teams/383"},"news" :{"href" :"http://api.espn.com/v1/sports/soccer/eng.1/teams/383/news"},"notes" :{"href" :"http://api.espn.com/v1/sports/soccer/eng.1/teams/383/news/notes"}},"web" :{"teams" :{"href" :"http://espnfc.com/team/_/id/383/west-bromwich-albion?ex_cid=espnapi_public"}}}},{"id" :384,"uid" :"s:600~t:384","location" :"Crystal Palace","name" :"Crystal Palace","nickname" :"Eagles","abbreviation" :"CRY","color" :"C60000","links" :{"api" :{"teams" :{"href" :"http://api.espn.com/v1/sports/soccer/eng.1/teams/384"},"news" :{"href" :"http://api.espn.com/v1/sports/soccer/eng.1/teams/384/news"},"notes" :{"href" :"http://api.espn.com/v1/sports/soccer/eng.1/teams/384/news/notes"}},"web" :{"teams" :{"href" :"http://espnfc.com/team/_/id/384/crystal-palace?ex_cid=espnapi_public"}}}}]}]}],"resultsOffset" :0,"resultsLimit" :50,"resultsCount" :20,"timestamp" :"2014-05-26T19:17:55Z","status" :"success"}