[
  { "home": "Argentina", "away": "Brazil", "homescore": "1", "awayscore": "1" },
  {
    "home": "United States",
    "away": "St. Vincent and the Grenadines",
    "homescore": "6",
    "awayscore": "1"
  },
  { "home": "Mexico", "away": "El Salvador", "homescore": "2", "awayscore": "0" },
  {
    "home": "Bosnia and Herzegovina",
    "away": "Republic of Ireland",
    "homescore": "1",
    "awayscore": "1"
  },
  { "home": "Spain", "away": "England", "homescore": "2", "awayscore": "0" },
  { "home": "Belgium", "away": "Italy", "homescore": "3", "awayscore": "1" },
  { "home": "France", "away": "Germany", "homescore": "2", "awayscore": "0" },
  {
    "home": "Bosnia and Herzegovina",
    "away": "Republic of Ireland",
    "homescore": "1",
    "awayscore": "1"
  },
  { "home": "Argentina", "away": "Brazil", "homescore": "1", "awayscore": "1" },
  { "home": "Peru", "away": "Paraguay", "homescore": "1", "awayscore": "0" },
  { "home": "Qatar", "away": "Turkey", "homescore": "1", "awayscore": "2" },
  { "home": "Luxembourg", "away": "Greece", "homescore": "1", "awayscore": "0" },
  { "home": "Czech Republic", "away": "Serbia", "homescore": "4", "awayscore": "1" },
  { "home": "Belgium", "away": "Italy", "homescore": "3", "awayscore": "1" },
  { "home": "Wales", "away": "Netherlands", "homescore": "2", "awayscore": "3" },
  { "home": "Northern Ireland", "away": "Latvia", "homescore": "1", "awayscore": "0" },
  { "home": "Poland", "away": "Iceland", "homescore": "4", "awayscore": "2" },
  { "home": "Slovakia", "away": "Switzerland", "homescore": "3", "awayscore": "2" },
  { "home": "Spain", "away": "England", "homescore": "2", "awayscore": "0" },
  { "home": "France", "away": "Germany", "homescore": "2", "awayscore": "0" },
  {
    "home": "United States",
    "away": "St. Vincent and the Grenadines",
    "homescore": "6",
    "awayscore": "1"
  },
  { "home": "Guatemala", "away": "Trinidad and Tobago", "homescore": "1", "awayscore": "2" },
  { "home": "Mexico", "away": "El Salvador", "homescore": "2", "awayscore": "0" },
  { "home": "Costa Rica", "away": "Haiti" },
  { "home": "Jamaica", "away": "Panama", "homescore": "0", "awayscore": "1" },
  { "home": "Canada", "away": "Honduras" },
  { "home": "Madagascar", "away": "Senegal", "homescore": "2", "awayscore": "2" },
  { "home": "Comoros Islands", "away": "Ghana", "homescore": "0", "awayscore": "0" },
  { "home": "Kenya", "away": "Cape Verde Islands", "homescore": "1", "awayscore": "0" },
  { "home": "Libya", "away": "Rwanda", "homescore": "1", "awayscore": "0" },
  { "home": "Angola", "away": "South Africa", "homescore": "1", "awayscore": "3" },
  { "home": "Niger", "away": "Cameroon", "homescore": "0", "awayscore": "3" },
  { "home": "Liberia", "away": "Ivory Coast", "homescore": "0", "awayscore": "1" },
  { "home": "Mauritania", "away": "Tunisia", "homescore": "1", "awayscore": "2" },
  { "home": "Swaziland", "away": "Nigeria", "homescore": "0", "awayscore": "0" },
  { "home": "T.N.S.", "away": "Rhyl", "homescore": "2", "awayscore": "2" },
  { "home": "Almagro", "away": "Atlanta", "homescore": "0", "awayscore": "0" },
  { "home": "Club Sportivo Italiano", "away": "Flandria", "homescore": "0", "awayscore": "0" },
  { "home": "San Carlos", "away": "Almirante Brown", "homescore": "0", "awayscore": "0" },
  { "home": "San Miguel", "away": "Excursionistas", "homescore": "0", "awayscore": "0" },
  { "home": "Lobos BUAP", "away": "Venados FC", "homescore": "0", "awayscore": "0" },
  { "home": "Mineros de Zacatecas", "away": "Atlante" },
  { "home": "Cafetaleros de Tapachula", "away": "Zacatepec" },
  { "home": "U. de G.", "away": "FC Juárez" },
  { "home": "Coras Tepic", "away": "Correcaminos" },
  { "home": "Cimarrones de Sonora", "away": "At. San Luis" },
  { "home": "Murcielagos FC", "away": "Necaxa" },
  { "home": "ABC", "away": "Mogi Mirim EC", "homescore": "3", "awayscore": "1" },
  { "home": "Oeste", "away": "Criciúma", "homescore": "1", "awayscore": "1" },
  { "home": "Paysandu SC", "away": "Luverdense", "homescore": "3", "awayscore": "2" },
  { "home": "Deportivo Pereira", "away": "Leones FC" },
  {
    "home": "Melbourne City FC",
    "away": "Western Sydney Wanderers",
    "homescore": "0",
    "awayscore": "3"
  },
  { "home": "Newcastle Jets", "away": "Central Coast Mariners" },
  { "home": "Albirex Niigata", "away": "Tampines Rovers", "homescore": "0", "awayscore": "1" },
  { "home": "Mumbai City FC", "away": "FC Pune City", "homescore": "0", "awayscore": "0" },
  { "home": "Alianza FC", "away": "Juventud Independiente" },
  { "home": "Universidad de El Salvador", "away": "CD Sonsonate" }
]